MANIFEST.in
README.md
beatcop.py
setup.py
BeatCop.egg-info/PKG-INFO
BeatCop.egg-info/SOURCES.txt
BeatCop.egg-info/dependency_links.txt
BeatCop.egg-info/top_level.txt