Metadata-Version: 1.1
Name: BeatCop
Version: 1.0
Summary: Cluster singleton manager
Home-page: https://github.com/Luluvise/BeatCop
Author: HoverHell
Author-email: hoverhell@gmail.com
License: UNKNOWN
Platform: UNKNOWN
Requires: redis(>=2.9.1)
